tercol/__init__.py
tercol/__main__.py
tercol-1.0.0.dist-info/licenses/LICENSE
tercol-1.0.0.dist-info/METADATA
tercol-1.0.0.dist-info/WHEEL
tercol-1.0.0.dist-info/top_level.txt
tercol-1.0.0.dist-info/RECORD
