Metadata-Version: 2.4
Name: tercol
Version: 1.0.0
Summary: DEPRECATED!!! Use tranci instead!
Author-email: Butterroach <butterroach@outlook.com>
Project-URL: Homepage, https://butterroach.github.io/tercol
Project-URL: Bug Tracker, https://github.com/butterroach/tercol/issues
Project-URL: Source Code, https://github.com/butterroach/tercol
Classifier: Development Status :: 7 - Inactive
Classifier: Intended Audience :: Developers
Classifier: Programming Language :: Python :: 3
Classifier: License :: OSI Approved :: MIT License
Classifier: Operating System :: OS Independent
Requires-Python: >=3.7
License-File: LICENSE
Dynamic: license-file
